mac_chng/__init__.py
mac_chng/main.py
mac_chng-0.1.1.dist-info/METADATA
mac_chng-0.1.1.dist-info/WHEEL
mac_chng-0.1.1.dist-info/RECORD
